crossbench/__init__.py
crossbench/benchmarks/__init__.py
crossbench/benchmarks/all.py
crossbench/benchmarks/base.py
crossbench/benchmarks/experimental/__init__.py
crossbench/benchmarks/experimental/power/__init__.py
crossbench/benchmarks/experimental/power/analysis/__init__.py
crossbench/benchmarks/experimental/power/analysis/power_result_parser.py
crossbench/benchmarks/experimental/power/analysis/power_result_parser_test.py
crossbench/benchmarks/experimental/power/analysis/test_data/powersampler.power_battery.json
crossbench/benchmarks/experimental/power/browsing_story.hjson
crossbench/benchmarks/experimental/power/browsing_urls.txt
crossbench/benchmarks/experimental/power/meet_story.hjson
crossbench/benchmarks/experimental/power/netflix_story.hjson
crossbench/benchmarks/experimental/power/power_benchmark.py
crossbench/benchmarks/experimental/power/power_sampler_config_example.hjson
crossbench/benchmarks/jetstream/__init__.py
crossbench/benchmarks/jetstream/jetstream_2.py
crossbench/benchmarks/jetstream/jetstream_2_0.py
crossbench/benchmarks/jetstream/jetstream_2_1.py
crossbench/benchmarks/jetstream/jetstream_2_2.py
crossbench/benchmarks/loading/__init__.py
crossbench/benchmarks/loading/action.py
crossbench/benchmarks/loading/action_runner/__init__.py
crossbench/benchmarks/loading/action_runner/android_input_action_runner.py
crossbench/benchmarks/loading/action_runner/base.py
crossbench/benchmarks/loading/action_runner/basic_action_runner.py
crossbench/benchmarks/loading/action_runner/chromeos_input_action_runner.py
crossbench/benchmarks/loading/action_runner/config.py
crossbench/benchmarks/loading/loading_benchmark.py
crossbench/benchmarks/loading/page.py
crossbench/benchmarks/loading/page_config.py
crossbench/benchmarks/loading/playback_controller.py
crossbench/benchmarks/manual/__init__.py
crossbench/benchmarks/manual/manual_benchmark.py
crossbench/benchmarks/motionmark/__init__.py
crossbench/benchmarks/motionmark/base.py
crossbench-1.0.5.dist-info/LICENSE
crossbench-1.0.5.dist-info/METADATA
crossbench-1.0.5.dist-info/WHEEL
crossbench-1.0.5.dist-info/entry_points.txt
crossbench-1.0.5.dist-info/RECORD
