Metadata-Version: 2.1
Name: crossbench
Version: 1.0.5
Summary: A cross-browser, cross-system web benchmark runner
License: BSD-3-Clause
Author: Camillo Bruni
Author-email: cbruni@chromium.org
Requires-Python: >=3.8,<3.12
Classifier: License :: OSI Approved :: BSD License
Classifier: Operating System :: OS Independent
Classifier: Programming Language :: Python :: 3
Classifier: Programming Language :: Python :: 3.8
Classifier: Programming Language :: Python :: 3.9
Classifier: Programming Language :: Python :: 3.10
Classifier: Programming Language :: Python :: 3.11
Requires-Dist: colorama (>=0.4.6,<0.5.0)
Requires-Dist: hjson (>=3.1.0,<4.0.0)
Requires-Dist: immutabledict (>=4.1.0,<5.0.0)
Requires-Dist: ordered-set (>=4.1.0,<5.0.0)
Requires-Dist: psutil (>=5.9.1,<6.0.0)
Requires-Dist: selenium (>=4.1.0,<5.0.0)
Requires-Dist: tabulate (>=0.8.10,<0.9.0)
Requires-Dist: websockets (>=11.0.3,<12.0.0)
Project-URL: Bug Tracker, http://bugs.crossben.ch
Project-URL: Homepage, http://crossben.ch
Project-URL: Source, http://source.crossben.ch
Project-URL: User Mailing list, http://mail.crossben.ch
